ax3_redactor-3.0.2.dist-info/licenses/LICENSE
redactor/__init__.py
redactor/mixins.py
redactor/models.py
redactor/urls.py
redactor/views.py
redactor/migrations/0001_initial.py
redactor/migrations/__init__.py
redactor/static/redactor/admin-redactor.css
redactor/static/redactor/admin-redactor.js
ax3_redactor-3.0.2.dist-info/METADATA
ax3_redactor-3.0.2.dist-info/WHEEL
ax3_redactor-3.0.2.dist-info/top_level.txt
ax3_redactor-3.0.2.dist-info/RECORD
