Metadata-Version: 2.4
Name: ax3-redactor
Version: 3.0.2
Summary: A Django app to add support for the redactor editor
Author-email: axiacore <info@axiacore.com>
License-Expression: MIT
Requires-Python: >=3.12
License-File: LICENSE
Dynamic: license-file
